polygon_api/__init__.py
polygon_api/api.py
polygon_api-1.0.0.dist-info/LICENSE
polygon_api-1.0.0.dist-info/METADATA
polygon_api-1.0.0.dist-info/WHEEL
polygon_api-1.0.0.dist-info/top_level.txt
polygon_api-1.0.0.dist-info/RECORD
