Metadata-Version: 2.1
Name: polygon_api
Version: 1.0.0
Summary: Python wrapper for Polygon API (polygon.codeforces.com)
Home-page: https://github.com/citxx/polygon-py
Author: Artem Tabolin
Author-email: artemtab@gmail.com
Classifier: Programming Language :: Python :: 3
Classifier: License :: OSI Approved :: MIT License
Classifier: Operating System :: OS Independent
Requires-Python: >=3.5
License-File: LICENSE
Requires-Dist: requests
